django_localizer/__init__.py
django_localizer/apps.py
django_localizer/management/__init__.py
django_localizer/management/commands/__init__.py
django_localizer/management/commands/generate_localizations.py
django_localizer/settings.py
django_localizer/templatetags/__init__.py
django_localizer/templatetags/translate.py
django_localizer/translate.py
django_localizer-0.1.10.dist-info/LICENSE
django_localizer-0.1.10.dist-info/WHEEL
django_localizer-0.1.10.dist-info/METADATA
django_localizer-0.1.10.dist-info/RECORD
