Metadata-Version: 2.1
Name: django-localizer
Version: 0.1.10
Summary: A library for making localizing django apps easier
Author: Timofey Danshin
Author-email: t.danshin@gmail.com
Requires-Python: >=3.6,<4.0
Classifier: Programming Language :: Python :: 3
Classifier: Programming Language :: Python :: 3.6
Classifier: Programming Language :: Python :: 3.7
Classifier: Programming Language :: Python :: 3.8
Requires-Dist: Django (>1.10,<4.0)
Requires-Dist: stew (>=0.1.2,<0.2.0)
